openImageDatasetSDKNoDependency-1.0.1.dist-info/DESCRIPTION.rst
openImageDatasetSDKNoDependency-1.0.1.dist-info/METADATA
openImageDatasetSDKNoDependency-1.0.1.dist-info/RECORD
openImageDatasetSDKNoDependency-1.0.1.dist-info/WHEEL
openImageDatasetSDKNoDependency-1.0.1.dist-info/metadata.json
openImageDatasetSDKNoDependency-1.0.1.dist-info/top_level.txt
openimagedataset/__init__.py
openimagedataset/_open_image.py
openimagedataset/environ.py
openimagedataset/_utils/__init__.py
openimagedataset/_utils/image_annotation_table_loader.py
openimagedataset/_utils/image_common_types.py
openimagedataset/_utils/image_downloader.py
openimagedataset/_utils/image_selector.py
openimagedataset/_utils/telemetry_utils.py
openimagedataset/dataaccess/__init__.py
openimagedataset/dataaccess/_open_image_blob_info.py
